twitter.common.options-0.3.10-py2.7-nspkg.pth
twitter/common/options/__init__.py
twitter/common/options/twitter_option.py
twitter.common.options-0.3.10.dist-info/DESCRIPTION.rst
twitter.common.options-0.3.10.dist-info/METADATA
twitter.common.options-0.3.10.dist-info/RECORD
twitter.common.options-0.3.10.dist-info/WHEEL
twitter.common.options-0.3.10.dist-info/metadata.json
twitter.common.options-0.3.10.dist-info/namespace_packages.txt
twitter.common.options-0.3.10.dist-info/top_level.txt
twitter.common.options-0.3.10.dist-info/zip-safe
