Metadata-Version: 2.0
Name: twitter.common.options
Version: 0.3.10
Summary: twitter.common optparse wrapper.
Home-page: https://github.com/twitter/commons
Author: UNKNOWN
Author-email: UNKNOWN
License: Apache License, Version 2.0
Platform: UNKNOWN
Classifier: Intended Audience :: Developers
Classifier: License :: OSI Approved :: Apache Software License
Classifier: Operating System :: OS Independent
Classifier: Programming Language :: Python
